KB_Bank_Transaction_Lookup/__init__.py
KB_Bank_Transaction_Lookup/crawler.py
KB_Bank_Transaction_Lookup/image_checker.py
KB_Bank_Transaction_Lookup/assets/0.png
KB_Bank_Transaction_Lookup/assets/5.png
KB_Bank_Transaction_Lookup/assets/7.png
KB_Bank_Transaction_Lookup/assets/8.png
KB_Bank_Transaction_Lookup/assets/9.png
KB_Bank_Transaction_Lookup-0.0.5.dist-info/METADATA
KB_Bank_Transaction_Lookup-0.0.5.dist-info/WHEEL
KB_Bank_Transaction_Lookup-0.0.5.dist-info/top_level.txt
KB_Bank_Transaction_Lookup-0.0.5.dist-info/RECORD
